cg3d_maya_casc-1.6.1.dist-info/licenses/LICENSE
cg3dcasc/Cascadeur.ui
cg3dcasc/__init__.py
cg3dcasc/editor.py
cg3dcasc/install_pymel.py
cg3dcasc/maya_casc_installer.py
cg3dcasc/userSetup.py
cg3dcasc/casc-site/cg3dcmds/__init__.py
cg3dcasc/casc-site/cg3dcmds/add_selected.py
cg3dcasc/casc-site/cg3dcmds/create_new_set.py
cg3dcasc/casc-site/cg3dcmds/export_animation.py
cg3dcasc/casc-site/cg3dcmds/remove_selected.py
cg3dcasc/casc-site/cg3dcmds/select_set_members.py
cg3dcasc/casc-site/cg3dcmds/sync_ids.py
cg3dcasc/casc-site/cg3dmaya/__init__.py
cg3dcasc/casc-site/cg3dmaya/client.py
cg3dcasc/casc-site/cg3dmaya/common.py
cg3dcasc/casc-site/cg3dmaya/fbx.py
cg3dcasc/casc-site/cg3dmaya/maya_export.py
cg3dcasc/casc-site/cg3dmaya/maya_import.py
cg3dcasc/casc-site/cg3dmaya/server.py
cg3dcasc/core/__init__.py
cg3dcasc/core/casc_export.py
cg3dcasc/core/casc_import.py
cg3dcasc/core/casc_qrt.py
cg3dcasc/core/client.py
cg3dcasc/core/command_port.py
cg3dcasc/core/common.py
cg3dcasc/core/fbx.py
cg3dcasc/core/hik.py
cg3dcasc/core/materials.py
cg3dcasc/core/server.py
cg3dcasc/core/udata.py
cg3dcasc/core/utils.py
cg3dcasc/menu/__init__.py
cg3dcasc/menu/connect.py
cg3dcasc/menu/editor.py
cg3dcasc/menu/import.py
cg3dcasc/menu/preferences.py
cg3dcasc/menu/quick_export.py
cg3dcasc/menu/add_to/__init__.py
cg3dcasc/menu/add_to/current_scene.py
cg3dcasc/menu/add_to/new_scene.py
cg3dcasc/menu/update/__init__.py
cg3dcasc/menu/update/update_animations.py
cg3dcasc/menu/update/update_models.py
cg3dcasc/menu/update/update_textures.py
cg3dcasc/menu/utils/__init__.py
cg3dcasc/menu/utils/constrain_proxy.py
cg3dcasc/menu/utils/convert_textures.py
cg3dcasc/menu/utils/create_proxy_rig.py
cg3dcasc/menu/utils/hik_from_proxy.py
cg3dcasc/menu/utils/sync_casc_id.py
cg3dcasc/preferences/__init__.py
cg3dcasc/preferences/core.py
cg3dcasc/preferences/editor.py
cg3dcasc/preferences/preferences.ui
cg3d_maya_casc-1.6.1.dist-info/METADATA
cg3d_maya_casc-1.6.1.dist-info/WHEEL
cg3d_maya_casc-1.6.1.dist-info/top_level.txt
cg3d_maya_casc-1.6.1.dist-info/RECORD
