Metadata-Version: 2.4
Name: cg3d-maya-casc
Version: 1.6.1
Summary: Easily bridge data between Maya and Cascadeur with this Maya Module
Author-email: Nathaniel A <developer@3dcg.guru>
Project-URL: Homepage, https://github.com/Nathanieljla/cg3d-maya-casc
Classifier: Programming Language :: Python :: 3
Classifier: Operating System :: OS Independent
Requires-Python: >=3.4
License-File: LICENSE
Requires-Dist: pymel>=1.5.0
Requires-Dist: cg3d-maya-core==0.7.0
Requires-Dist: wing-carrier==1.2.0
Dynamic: license-file
